odl/VERSION
odl/__init__.py
odl/pytest.ini
odl/contrib/__init__.py
odl/contrib/datasets/__init__.py
odl/contrib/datasets/util.py
odl/contrib/datasets/ct/__init__.py
odl/contrib/datasets/ct/fips.py
odl/contrib/datasets/ct/mayo.py
odl/contrib/datasets/ct/mayo_dicom_dict.py
odl/contrib/datasets/images/__init__.py
odl/contrib/datasets/images/cambridge.py
odl/contrib/datasets/mri/__init__.py
odl/contrib/datasets/mri/tugraz.py
odl/contrib/fom/__init__.py
odl/contrib/fom/supervised.py
odl/contrib/fom/unsupervised.py
odl/contrib/fom/util.py
odl/contrib/param_opt/__init__.py
odl/contrib/param_opt/param_opt.py
odl/contrib/pyshearlab/__init__.py
odl/contrib/pyshearlab/pyshearlab_operator.py
odl/contrib/shearlab/__init__.py
odl/contrib/shearlab/shearlab_operator.py
odl/contrib/solvers/__init__.py
odl/contrib/solvers/functional/__init__.py
odl/contrib/solvers/functional/nonlocalmeans_functionals.py
odl/contrib/solvers/operator/__init__.py
odl/contrib/solvers/operator/proximal_lang.py
odl/contrib/solvers/spdhg/__init__.py
odl/contrib/solvers/spdhg/misc.py
odl/contrib/solvers/spdhg/stochastic_primal_dual_hybrid_gradient.py
odl/contrib/tensorflow/__init__.py
odl/contrib/tensorflow/layer.py
odl/contrib/tensorflow/operator.py
odl/contrib/tensorflow/space.py
odl/contrib/theano/__init__.py
odl/contrib/theano/layer.py
odl/contrib/tomo/__init__.py
odl/contrib/tomo/elekta.py
odl/contrib/torch/__init__.py
odl/contrib/torch/operator.py
odl/deform/__init__.py
odl/deform/linearized.py
odl/diagnostics/__init__.py
odl/diagnostics/examples.py
odl/diagnostics/operator.py
odl/diagnostics/space.py
odl/discr/__init__.py
odl/discr/diff_ops.py
odl/discr/discr_ops.py
odl/discr/discr_space.py
odl/discr/discr_utils.py
odl/discr/grid.py
odl/discr/partition.py
odl/operator/__init__.py
odl/operator/default_ops.py
odl/operator/operator.py
odl/operator/oputils.py
odl/operator/pspace_ops.py
odl/operator/tensor_ops.py
odl/phantom/__init__.py
odl/phantom/emission.py
odl/phantom/geometric.py
odl-0.8.3.dist-info/licenses/LICENSE
odl-0.8.3.dist-info/METADATA
odl-0.8.3.dist-info/WHEEL
odl-0.8.3.dist-info/entry_points.txt
odl-0.8.3.dist-info/top_level.txt
odl-0.8.3.dist-info/RECORD
