Metadata-Version: 2.4
Name: odl
Version: 0.8.3
Summary: Operator Discretization Library
Home-page: https://github.com/odlgroup/odl
Download-URL: https://github.com/odlgroup/odl/archive/master.zip
Author: Jonas Adler, Holger Kohr, and the ODL Contributors
Author-email: odl@math.kth.se
License: MPL-2.0
Keywords: research,development,mathematics,prototyping,imaging,tomography
Platform: any
Classifier: Development Status :: 4 - Beta
Classifier: Intended Audience :: Developers
Classifier: Intended Audience :: Science/Research
Classifier: Intended Audience :: Education
Classifier: Topic :: Scientific/Engineering
Classifier: Topic :: Scientific/Engineering :: Mathematics
Classifier: Topic :: Scientific/Engineering :: Artificial Intelligence
Classifier: Topic :: Scientific/Engineering :: Physics
Classifier: Topic :: Scientific/Engineering :: Medical Science Apps.
Classifier: Topic :: Software Development
Classifier: Topic :: Software Development :: Libraries
Classifier: Topic :: Software Development :: Libraries :: Python Modules
Classifier: License :: OSI Approved :: Mozilla Public License 2.0 (MPL 2.0)
Classifier: Programming Language :: Python :: 3.7
Classifier: Programming Language :: Python :: 3.8
Classifier: Programming Language :: Python :: 3.9
Classifier: Programming Language :: Python :: 3.10
Classifier: Programming Language :: Python :: 3.11
Classifier: Programming Language :: Python :: 3.12
Classifier: Operating System :: OS Independent
Requires-Python: >=3.7
License-File: LICENSE
Requires-Dist: setuptools>=65.6
Requires-Dist: future>=0.16
Requires-Dist: packaging>=17.0
Requires-Dist: numpy<2.2,>=1.19
Requires-Dist: scipy>=1.1
Provides-Extra: testing
Requires-Dist: pytest<5.0,>=3.1; python_version <= "2.7" and extra == "testing"
Requires-Dist: pytest>=5.4.0; python_version >= "3" and extra == "testing"
Requires-Dist: coverage>=4.0; extra == "testing"
Requires-Dist: coveralls; extra == "testing"
Provides-Extra: all
Requires-Dist: pytest<5.0,>=3.1; python_version <= "2.7" and extra == "all"
Requires-Dist: pytest>=5.4.0; python_version >= "3" and extra == "all"
Requires-Dist: coverage>=4.0; extra == "all"
Requires-Dist: coveralls; extra == "all"
Requires-Dist: matplotlib; extra == "all"
Requires-Dist: pyfftw; extra == "all"
Requires-Dist: pywavelets>=1.0.1; extra == "all"
Requires-Dist: scikit-image; extra == "all"
Dynamic: download-url
Dynamic: license-file
